setup.cfg
setup.py
django_npm_36.egg-info/PKG-INFO
django_npm_36.egg-info/SOURCES.txt
django_npm_36.egg-info/dependency_links.txt
django_npm_36.egg-info/requires.txt
django_npm_36.egg-info/top_level.txt
npm/__init__.py
npm/finders.py
npm/management/__init__.py
npm/management/commands/__init__.py
npm/management/commands/npm_install.py