Metadata-Version: 1.1
Name: django-npm-36
Version: 1.0.0
Summary: A temp compat. version of django-npm
Home-page: https://github.com/pattyjogal/django-npm
Author: Patrick Gallagher
Author-email: patrickj@cpgallagher.compile
License: MIT
Keywords: django npm staticfiles
Platform: UNKNOWN
Classifier: Development Status :: 3 - Alpha
Classifier: Intended Audience :: Developers
Classifier: Topic :: Software Development :: Build Tools
Classifier: License :: OSI Approved :: MIT License
Classifier: Programming Language :: Python :: 2
Classifier: Programming Language :: Python :: 2.6
Classifier: Programming Language :: Python :: 2.7
Classifier: Programming Language :: Python :: 3
Classifier: Programming Language :: Python :: 3.2
Classifier: Programming Language :: Python :: 3.3
Classifier: Programming Language :: Python :: 3.4
Classifier: Programming Language :: Python :: 3.5
Classifier: Programming Language :: Python :: 3.6
